{
    "created_time": "2024-08-08T09:06:04Z",
    "files": [
        {
            "attachment_folder": "",
            "created_time": "2024-08-08T09:06:19Z",
            "id": "322",
            "modified_time": "2024-08-09T06:57:57Z",
            "name": "tenda_ac15_stackflow_formDLNAserver.md",
            "signature": "856341185473841803",
            "tags": [
            ]
        }
    ],
    "folders": [
    ],
    "id": "321",
    "modified_time": "2024-08-08T09:06:04Z",
    "signature": "2298088992944720508",
    "version": 3
}
